biblioteca_calculadora_simples/__init__.py
biblioteca_calculadora_simples/calculadora_simples.py
biblioteca_calculadora_simples_nersant-0.1.0.dist-info/METADATA
biblioteca_calculadora_simples_nersant-0.1.0.dist-info/WHEEL
biblioteca_calculadora_simples_nersant-0.1.0.dist-info/top_level.txt
biblioteca_calculadora_simples_nersant-0.1.0.dist-info/RECORD
