Metadata-Version: 2.4
Name: biblioteca-calculadora-simples-nersant
Version: 0.1.0
Summary: Uma biblioteca com funções de calculadora simples criada no curso
Author-email: Marcelo Kamei <marcelokamei78@gmail.com>
License: MIT
Requires-Python: >=3.8
